qrlib/__init__.py
qrlib/api/__init__.py
qrlib/api/app.py
qrlib/api/config.toml
qrlib/api/dbCLI.py
qrlib/api/rpl_config.py
qrlib/api/schema.prisma
qrlib/api/common/__init__.py
qrlib/api/common/models.py
qrlib/api/routers/__init__.py
qrlib/api/routers/channel.py
qrlib/scripts/__init__.py
qrlib/scripts/run_api.py
qmlib-0.0.1.dist-info/METADATA
qmlib-0.0.1.dist-info/WHEEL
qmlib-0.0.1.dist-info/entry_points.txt
qmlib-0.0.1.dist-info/licenses/LICENSE
qmlib-0.0.1.dist-info/RECORD
